tests/__init__.py
tests/test_attachments.py
wagtail_attachments/__init__.py
wagtail_attachments/apps.py
wagtail_attachments/auxiliaries.py
wagtail_attachments/default_settings.py
wagtail_attachments/panels.py
wagtail_attachments/migrations/0001_initial.py
wagtail_attachments/migrations/0002_add_attachment_roles.py
wagtail_attachments/migrations/__init__.py
wagtail_attachments/models/__init__.py
wagtail_attachments/models/attachment_fields.py
wagtail_attachments/models/attachment_roles.py
wagtail_attachments/models/attachments.py
wagtail_attachments/models/mixins.py
wagtail_attachments/templates/wagtail_attachments/support_tag.html
wagtail_attachments-4.1.0.dist-info/AUTHORS.txt
wagtail_attachments-4.1.0.dist-info/LICENSE.txt
wagtail_attachments-4.1.0.dist-info/METADATA
wagtail_attachments-4.1.0.dist-info/WHEEL
wagtail_attachments-4.1.0.dist-info/top_level.txt
wagtail_attachments-4.1.0.dist-info/RECORD
